mellifera/__init__.py
mellifera/executor.py
mellifera/executors/__init__.py
mellifera/executors/nsmainthread.py
mellifera/executors/trio.py
mellifera/orchestrator.py
mellifera/service.py
mellifera/services/__init__.py
mellifera/services/nsmainthread.py
mellifera/services/trio.py
mellifera-0.5.1.dist-info/WHEEL
mellifera-0.5.1.dist-info/METADATA
mellifera-0.5.1.dist-info/RECORD
