Metadata-Version: 2.3
Name: mellifera
Version: 0.5.1
Summary: Runs async services under trio and orchestrates them with a pyobjc NSMainThread service
Requires-Dist: pyobjc-core>=12.1 ; sys_platform == 'darwin'
Requires-Dist: trio>=0.32.0
Requires-Python: >=3.10
